{
    "location": {
        "name": "London",
        "region": "City of London, Greater London",
        "country": "United Kingdom",
        "lat": 51.5171,
        "lon": -0.1062,
        "tz_id": "Europe/London",
        "localtime_epoch": 1735435832,
        "localtime": "2024-12-29 01:30"
    },
    "current": {
        "last_updated_epoch": 1735435800,
        "last_updated": "2024-12-29 01:30",
        "temp_c": 5.2,
        "temp_f": 41.4,
        "is_day": 0,
        "condition": {
            "text": "Overcast",
            "icon": "//cdn.weatherapi.com/weather/64x64/night/122.png",
            "code": 1009
        },
        "wind_mph": 3.6,
        "wind_kph": 5.8,
        "wind_degree": 273,
        "wind_dir": "W",
        "pressure_mb": 1029,
        "pressure_in": 30.39,
        "precip_mm": 0,
        "precip_in": 0,
        "humidity": 93,
        "cloud": 100,
        "feelslike_c": 4,
        "feelslike_f": 39.3,
        "windchill_c": 2.8,
        "windchill_f": 37.1,
        "heatindex_c": 4.1,
        "heatindex_f": 39.4,
        "dewpoint_c": 3.2,
        "dewpoint_f": 37.7,
        "vis_km": 10,
        "vis_miles": 6,
        "uv": 0,
        "gust_mph": 6.2,
        "gust_kph": 10
    },
    "forecast": {
        "forecastday": [
            {
                "date": "2024-12-29",
                "date_epoch": 1735430400,
                "day": {
                    "maxtemp_c": 7.9,
                    "maxtemp_f": 46.1,
                    "mintemp_c": 3.9,
                    "mintemp_f": 39.1,
                    "avgtemp_c": 5.4,
                    "avgtemp_f": 41.7,
                    "maxwind_mph": 6,
                    "maxwind_kph": 9.7,
                    "totalprecip_mm": 0,
                    "totalprecip_in": 0,
                    "totalsnow_cm": 0,
                    "avgvis_km": 5,
                    "avgvis_miles": 3,
                    "avghumidity": 93,
                    "daily_will_it_rain": 0,
                    "daily_chance_of_rain": 0,
                    "daily_will_it_snow": 0,
                    "daily_chance_of_snow": 0,
                    "condition": {
                        "text": "Mist",
                        "icon": "//cdn.weatherapi.com/weather/64x64/day/143.png",
                        "code": 1030
                    },
                    "uv": 0.1
                },
                "astro": {
                    "sunrise": "08:06 AM",
                    "sunset": "03:59 PM",
                    "moonrise": "07:24 AM",
                    "moonset": "02:00 PM",
                    "moon_phase": "Waning Crescent",
                    "moon_illumination": 4,
                    "is_moon_up": 0,
                    "is_sun_up": 0
                },
                "hour": [
                    {
                        "time_epoch": 1735430400,
                        "time": "2024-12-29 00:00",
                        "temp_c": 4.3,
                        "temp_f": 39.7,
                        "is_day": 0,
                        "condition": {
                            "text": "Partly Cloudy ",
                            "icon": "//cdn.weatherapi.com/weather/64x64/night/116.png",
                            "code": 1003
                        },
                        "wind_mph": 3.4,
                        "wind_kph": 5.4,
                        "wind_degree": 270,
                        "wind_dir": "W",
                        "pressure_mb": 1029,
                        "pressure_in": 30.37,
                        "precip_mm": 0,
                        "precip_in": 0,
                        "snow_cm": 0,
                        "humidity": 93,
                        "cloud": 40,
                        "feelslike_c": 3.1,
                        "feelslike_f": 37.6,
                        "windchill_c": 3.1,
                        "windchill_f": 37.6,
                        "heatindex_c": 4.3,
                        "heatindex_f": 39.7,
                        "dewpoint_c": 3.2,
                        "dewpoint_f": 37.7,
                        "will_it_rain": 0,
                        "chance_of_rain": 0,
                        "will_it_snow": 0,
                        "chance_of_snow": 0,
                        "vis_km": 10,
                        "vis_miles": 6,
                        "gust_mph": 5.8,
                        "gust_kph": 9.3,
                        "uv": 0
                    },
                    {
                        "time_epoch": 1735434000,
                        "time": "2024-12-29 01:00",
                        "temp_c": 5.2,
                        "temp_f": 41.4,
                        "is_day": 0,
                        "condition": {
                            "text": "Overcast",
                            "icon": "//cdn.weatherapi.com/weather/64x64/night/122.png",
                            "code": 1009
                        },
                        "wind_mph": 3.6,
                        "wind_kph": 5.8,
                        "wind_degree": 273,
                        "wind_dir": "W",
                        "pressure_mb": 1029,
                        "pressure_in": 30.39,
                        "precip_mm": 0,
                        "precip_in": 0,
                        "snow_cm": 0,
                        "humidity": 93,
                        "cloud": 100,
                        "feelslike_c": 2.8,
                        "feelslike_f": 37.1,
                        "windchill_c": 2.8,
                        "windchill_f": 37.1,
                        "heatindex_c": 4.1,
                        "heatindex_f": 39.4,
                        "dewpoint_c": 3.2,
                        "dewpoint_f": 37.7,
                        "will_it_rain": 0,
                        "chance_of_rain": 0,
                        "will_it_snow": 0,
                        "chance_of_snow": 0,
                        "vis_km": 10,
                        "vis_miles": 6,
                        "gust_mph": 6.2,
                        "gust_kph": 10,
                        "uv": 0
                    },
                    {
                        "time_epoch": 1735437600,
                        "time": "2024-12-29 02:00",
                        "temp_c": 4.1,
                        "temp_f": 39.3,
                        "is_day": 0,
                        "condition": {
                            "text": "Mist",
                            "icon": "//cdn.weatherapi.com/weather/64x64/night/143.png",
                            "code": 1030
                        },
                        "wind_mph": 3.4,
                        "wind_kph": 5.4,
                        "wind_degree": 265,
                        "wind_dir": "W",
                        "pressure_mb": 1028,
                        "pressure_in": 30.37,
                        "precip_mm": 0,
                        "precip_in": 0,
                        "snow_cm": 0,
                        "humidity": 94,
                        "cloud": 40,
                        "feelslike_c": 2.9,
                        "feelslike_f": 37.2,
                        "windchill_c": 2.9,
                        "windchill_f": 37.2,
                        "heatindex_c": 4.1,
                        "heatindex_f": 39.3,
                        "dewpoint_c": 3.2,
                        "dewpoint_f": 37.8,
                        "will_it_rain": 0,
                        "chance_of_rain": 0,
                        "will_it_snow": 0,
                        "chance_of_snow": 0,
                        "vis_km": 2,
                        "vis_miles": 1,
                        "gust_mph": 6,
                        "gust_kph": 9.7,
                        "uv": 0
                    },
                    {
                        "time_epoch": 1735441200,
                        "time": "2024-12-29 03:00",
                        "temp_c": 4,
                        "temp_f": 39.2,
                        "is_day": 0,
                        "condition": {
                            "text": "Mist",
                            "icon": "//cdn.weatherapi.com/weather/64x64/night/143.png",
                            "code": 1030
                        },
                        "wind_mph": 3.4,
                        "wind_kph": 5.4,
                        "wind_degree": 258,
                        "wind_dir": "WSW",
                        "pressure_mb": 1028,
                        "pressure_in": 30.37,
                        "precip_mm": 0,
                        "precip_in": 0,
                        "snow_cm": 0,
                        "humidity": 95,
                        "cloud": 38,
                        "feelslike_c": 2.8,
                        "feelslike_f": 37.1,
                        "windchill_c": 2.8,
                        "windchill_f": 37.1,
                        "heatindex_c": 4,
                        "heatindex_f": 39.3,
                        "dewpoint_c": 3.3,
                        "dewpoint_f": 37.9,
                        "will_it_rain": 0,
                        "chance_of_rain": 0,
                        "will_it_snow": 0,
                        "chance_of_snow": 0,
                        "vis_km": 2,
                        "vis_miles": 1,
                        "gust_mph": 6.2,
                        "gust_kph": 10,
                        "uv": 0
                    },
                    {
                        "time_epoch": 1735444800,
                        "time": "2024-12-29 04:00",
                        "temp_c": 4,
                        "temp_f": 39.2,
                        "is_day": 0,
                        "condition": {
                            "text": "Mist",
                            "icon": "//cdn.weatherapi.com/weather/64x64/night/143.png",
                            "code": 1030
                        },
                        "wind_mph": 3.8,
                        "wind_kph": 6.1,
                        "wind_degree": 268,
                        "wind_dir": "W",
                        "pressure_mb": 1029,
                        "pressure_in": 30.37,
                        "precip_mm": 0,
                        "precip_in": 0,
                        "snow_cm": 0,
                        "humidity": 96,
                        "cloud": 38,
                        "feelslike_c": 2.6,
                        "feelslike_f": 36.6,
                        "windchill_c": 2.6,
                        "windchill_f": 36.6,
                        "heatindex_c": 4,
                        "heatindex_f": 39.2,
                        "dewpoint_c": 3.4,
                        "dewpoint_f": 38.1,
                        "will_it_rain": 0,
                        "chance_of_rain": 0,
                        "will_it_snow": 0,
                        "chance_of_snow": 0,
                        "vis_km": 2,
                        "vis_miles": 1,
                        "gust_mph": 7,
                        "gust_kph": 11.3,
                        "uv": 0
                    },
                    {
                        "time_epoch": 1735448400,
                        "time": "2024-12-29 05:00",
                        "temp_c": 4,
                        "temp_f": 39.1,
                        "is_day": 0,
                        "condition": {
                            "text": "Mist",
                            "icon": "//cdn.weatherapi.com/weather/64x64/night/143.png",
                            "code": 1030
                        },
                        "wind_mph": 3.6,
                        "wind_kph": 5.8,
                        "wind_degree": 262,
                        "wind_dir": "W",
                        "pressure_mb": 1029,
                        "pressure_in": 30.37,
                        "precip_mm": 0,
                        "precip_in": 0,
                        "snow_cm": 0,
                        "humidity": 96,
                        "cloud": 38,
                        "feelslike_c": 2.6,
                        "feelslike_f": 36.7,
                        "windchill_c": 2.6,
                        "windchill_f": 36.7,
                        "heatindex_c": 4,
                        "heatindex_f": 39.1,
                        "dewpoint_c": 3.4,
                        "dewpoint_f": 38.1,
                        "will_it_rain": 0,
                        "chance_of_rain": 0,
                        "will_it_snow": 0,
                        "chance_of_snow": 0,
                        "vis_km": 2,
                        "vis_miles": 1,
                        "gust_mph": 6.8,
                        "gust_kph": 10.9,
                        "uv": 0
                    },
                    {
                        "time_epoch": 1735452000,
                        "time": "2024-12-29 06:00",
                        "temp_c": 3.9,
                        "temp_f": 39.1,
                        "is_day": 0,
                        "condition": {
                            "text": "Mist",
                            "icon": "//cdn.weatherapi.com/weather/64x64/night/143.png",
                            "code": 1030
                        },
                        "wind_mph": 3.6,
                        "wind_kph": 5.8,
                        "wind_degree": 259,
                        "wind_dir": "W",
                        "pressure_mb": 1029,
                        "pressure_in": 30.38,
                        "precip_mm": 0,
                        "precip_in": 0,
                        "snow_cm": 0,
                        "humidity": 96,
                        "cloud": 33,
                        "feelslike_c": 2.6,
                        "feelslike_f": 36.6,
                        "windchill_c": 2.6,
                        "windchill_f": 36.6,
                        "heatindex_c": 3.9,
                        "heatindex_f": 39.1,
                        "dewpoint_c": 3.3,
                        "dewpoint_f": 38,
                        "will_it_rain": 0,
                        "chance_of_rain": 0,
                        "will_it_snow": 0,
                        "chance_of_snow": 0,
                        "vis_km": 2,
                        "vis_miles": 1,
                        "gust_mph": 7,
                        "gust_kph": 11.2,
                        "uv": 0
                    },
                    {
                        "time_epoch": 1735455600,
                        "time": "2024-12-29 07:00",
                        "temp_c": 4,
                        "temp_f": 39.2,
                        "is_day": 0,
                        "condition": {
                            "text": "Mist",
                            "icon": "//cdn.weatherapi.com/weather/64x64/night/143.png",
                            "code": 1030
                        },
                        "wind_mph": 3.8,
                        "wind_kph": 6.1,
                        "wind_degree": 246,
                        "wind_dir": "WSW",
                        "pressure_mb": 1029,
                        "pressure_in": 30.39,
                        "precip_mm": 0,
                        "precip_in": 0,
                        "snow_cm": 0,
                        "humidity": 96,
                        "cloud": 71,
                        "feelslike_c": 2.5,
                        "feelslike_f": 36.5,
                        "windchill_c": 2.5,
                        "windchill_f": 36.5,
                        "heatindex_c": 4,
                        "heatindex_f": 39.2,
                        "dewpoint_c": 3.4,
                        "dewpoint_f": 38.1,
                        "will_it_rain": 0,
                        "chance_of_rain": 0,
                        "will_it_snow": 0,
                        "chance_of_snow": 0,
                        "vis_km": 2,
                        "vis_miles": 1,
                        "gust_mph": 7.5,
                        "gust_kph": 12.1,
                        "uv": 0
                    },
                    {
                        "time_epoch": 1735459200,
                        "time": "2024-12-29 08:00",
                        "temp_c": 4,
                        "temp_f": 39.3,
                        "is_day": 0,
                        "condition": {
                            "text": "Mist",
                            "icon": "//cdn.weatherapi.com/weather/64x64/night/143.png",
                            "code": 1030
                        },
                        "wind_mph": 4,
                        "wind_kph": 6.5,
                        "wind_degree": 237,
                        "wind_dir": "WSW",
                        "pressure_mb": 1029,
                        "pressure_in": 30.39,
                        "precip_mm": 0,
                        "precip_in": 0,
                        "snow_cm": 0,
                        "humidity": 96,
                        "cloud": 67,
                        "feelslike_c": 2.5,
                        "feelslike_f": 36.4,
                        "windchill_c": 2.5,
                        "windchill_f": 36.4,
                        "heatindex_c": 4,
                        "heatindex_f": 39.3,
                        "dewpoint_c": 3.4,
                        "dewpoint_f": 38.1,
                        "will_it_rain": 0,
                        "chance_of_rain": 0,
                        "will_it_snow": 0,
                        "chance_of_snow": 0,
                        "vis_km": 2,
                        "vis_miles": 1,
                        "gust_mph": 8.1,
                        "gust_kph": 13,
                        "uv": 0
                    },
                    {
                        "time_epoch": 1735462800,
                        "time": "2024-12-29 09:00",
                        "temp_c": 4.3,
                        "temp_f": 39.8,
                        "is_day": 1,
                        "condition": {
                            "text": "Mist",
                            "icon": "//cdn.weatherapi.com/weather/64x64/day/143.png",
                            "code": 1030
                        },
                        "wind_mph": 4.3,
                        "wind_kph": 6.8,
                        "wind_degree": 237,
                        "wind_dir": "WSW",
                        "pressure_mb": 1030,
                        "pressure_in": 30.4,
                        "precip_mm": 0,
                        "precip_in": 0,
                        "snow_cm": 0,
                        "humidity": 95,
                        "cloud": 76,
                        "feelslike_c": 2.7,
                        "feelslike_f": 36.8,
                        "windchill_c": 2.7,
                        "windchill_f": 36.8,
                        "heatindex_c": 4.3,
                        "heatindex_f": 39.8,
                        "dewpoint_c": 3.6,
                        "dewpoint_f": 38.4,
                        "will_it_rain": 0,
                        "chance_of_rain": 0,
                        "will_it_snow": 0,
                        "chance_of_snow": 0,
                        "vis_km": 2,
                        "vis_miles": 1,
                        "gust_mph": 8.3,
                        "gust_kph": 13.3,
                        "uv": 0.1
                    },
                    {
                        "time_epoch": 1735466400,
                        "time": "2024-12-29 10:00",
                        "temp_c": 5.2,
                        "temp_f": 41.3,
                        "is_day": 1,
                        "condition": {
                            "text": "Cloudy ",
                            "icon": "//cdn.weatherapi.com/weather/64x64/day/119.png",
                            "code": 1006
                        },
                        "wind_mph": 4.3,
                        "wind_kph": 6.8,
                        "wind_degree": 231,
                        "wind_dir": "SW",
                        "pressure_mb": 1030,
                        "pressure_in": 30.41,
                        "precip_mm": 0,
                        "precip_in": 0,
                        "snow_cm": 0,
                        "humidity": 90,
                        "cloud": 77,
                        "feelslike_c": 3.6,
                        "feelslike_f": 38.6,
                        "windchill_c": 3.6,
                        "windchill_f": 38.6,
                        "heatindex_c": 5.2,
                        "heatindex_f": 41.3,
                        "dewpoint_c": 3.7,
                        "dewpoint_f": 38.7,
                        "will_it_rain": 0,
                        "chance_of_rain": 0,
                        "will_it_snow": 0,
                        "chance_of_snow": 0,
                        "vis_km": 10,
                        "vis_miles": 6,
                        "gust_mph": 7.5,
                        "gust_kph": 12.1,
                        "uv": 0.3
                    },
                    {
                        "time_epoch": 1735470000,
                        "time": "2024-12-29 11:00",
                        "temp_c": 6.2,
                        "temp_f": 43.2,
                        "is_day": 1,
                        "condition": {
                            "text": "Partly Cloudy ",
                            "icon": "//cdn.weatherapi.com/weather/64x64/day/116.png",
                            "code": 1003
                        },
                        "wind_mph": 4.7,
                        "wind_kph": 7.6,
                        "wind_degree": 234,
                        "wind_dir": "SW",
                        "pressure_mb": 1030,
                        "pressure_in": 30.41,
                        "precip_mm": 0,
                        "precip_in": 0,
                        "snow_cm": 0,
                        "humidity": 85,
                        "cloud": 51,
                        "feelslike_c": 4.7,
                        "feelslike_f": 40.4,
                        "windchill_c": 4.7,
                        "windchill_f": 40.4,
                        "heatindex_c": 6.2,
                        "heatindex_f": 43.2,
                        "dewpoint_c": 4,
                        "dewpoint_f": 39.1,
                        "will_it_rain": 0,
                        "chance_of_rain": 0,
                        "will_it_snow": 0,
                        "chance_of_snow": 0,
                        "vis_km": 10,
                        "vis_miles": 6,
                        "gust_mph": 7.5,
                        "gust_kph": 12,
                        "uv": 0.5
                    },
                    {
                        "time_epoch": 1735473600,
                        "time": "2024-12-29 12:00",
                        "temp_c": 7.1,
                        "temp_f": 44.8,
                        "is_day": 1,
                        "condition": {
                            "text": "Partly Cloudy ",
                            "icon": "//cdn.weatherapi.com/weather/64x64/day/116.png",
                            "code": 1003
                        },
                        "wind_mph": 5.1,
                        "wind_kph": 8.3,
                        "wind_degree": 244,
                        "wind_dir": "WSW",
                        "pressure_mb": 1030,
                        "pressure_in": 30.41,
                        "precip_mm": 0,
                        "precip_in": 0,
                        "snow_cm": 0,
                        "humidity": 82,
                        "cloud": 29,
                        "feelslike_c": 5.6,
                        "feelslike_f": 42,
                        "windchill_c": 5.6,
                        "windchill_f": 42,
                        "heatindex_c": 7.1,
                        "heatindex_f": 44.8,
                        "dewpoint_c": 4.3,
                        "dewpoint_f": 39.8,
                        "will_it_rain": 0,
                        "chance_of_rain": 0,
                        "will_it_snow": 0,
                        "chance_of_snow": 0,
                        "vis_km": 10,
                        "vis_miles": 6,
                        "gust_mph": 7.5,
                        "gust_kph": 12,
                        "uv": 0.6
                    },
                    {
                        "time_epoch": 1735477200,
                        "time": "2024-12-29 13:00",
                        "temp_c": 7.7,
                        "temp_f": 45.8,
                        "is_day": 1,
                        "condition": {
                            "text": "Sunny",
                            "icon": "//cdn.weatherapi.com/weather/64x64/day/113.png",
                            "code": 1000
                        },
                        "wind_mph": 5.6,
                        "wind_kph": 9,
                        "wind_degree": 240,
                        "wind_dir": "WSW",
                        "pressure_mb": 1029,
                        "pressure_in": 30.39,
                        "precip_mm": 0,
                        "precip_in": 0,
                        "snow_cm": 0,
                        "humidity": 81,
                        "cloud": 8,
                        "feelslike_c": 6.1,
                        "feelslike_f": 42.9,
                        "windchill_c": 6.1,
                        "windchill_f": 42.9,
                        "heatindex_c": 7.7,
                        "heatindex_f": 45.8,
                        "dewpoint_c": 4.7,
                        "dewpoint_f": 40.5,
                        "will_it_rain": 0,
                        "chance_of_rain": 0,
                        "will_it_snow": 0,
                        "chance_of_snow": 0,
                        "vis_km": 10,
                        "vis_miles": 6,
                        "gust_mph": 8,
                        "gust_kph": 12.9,
                        "uv": 0.5
                    },
                    {
                        "time_epoch": 1735480800,
                        "time": "2024-12-29 14:00",
                        "temp_c": 7.9,
                        "temp_f": 46.1,
                        "is_day": 1,
                        "condition": {
                            "text": "Sunny",
                            "icon": "//cdn.weatherapi.com/weather/64x64/day/113.png",
                            "code": 1000
                        },
                        "wind_mph": 5.4,
                        "wind_kph": 8.6,
                        "wind_degree": 232,
                        "wind_dir": "SW",
                        "pressure_mb": 1029,
                        "pressure_in": 30.38,
                        "precip_mm": 0,
                        "precip_in": 0,
                        "snow_cm": 0,
                        "humidity": 83,
                        "cloud": 7,
                        "feelslike_c": 6.3,
                        "feelslike_f": 43.4,
                        "windchill_c": 6.3,
                        "windchill_f": 43.4,
                        "heatindex_c": 7.9,
                        "heatindex_f": 46.1,
                        "dewpoint_c": 5.1,
                        "dewpoint_f": 41.1,
                        "will_it_rain": 0,
                        "chance_of_rain": 0,
                        "will_it_snow": 0,
                        "chance_of_snow": 0,
                        "vis_km": 10,
                        "vis_miles": 6,
                        "gust_mph": 8,
                        "gust_kph": 12.9,
                        "uv": 0.3
                    },
                    {
                        "time_epoch": 1735484400,
                        "time": "2024-12-29 15:00",
                        "temp_c": 7.5,
                        "temp_f": 45.5,
                        "is_day": 1,
                        "condition": {
                            "text": "Sunny",
                            "icon": "//cdn.weatherapi.com/weather/64x64/day/113.png",
                            "code": 1000
                        },
                        "wind_mph": 5.6,
                        "wind_kph": 9,
                        "wind_degree": 228,
                        "wind_dir": "SW",
                        "pressure_mb": 1029,
                        "pressure_in": 30.38,
                        "precip_mm": 0,
                        "precip_in": 0,
                        "snow_cm": 0,
                        "humidity": 87,
                        "cloud": 9,
                        "feelslike_c": 5.8,
                        "feelslike_f": 42.5,
                        "windchill_c": 5.8,
                        "windchill_f": 42.5,
                        "heatindex_c": 7.5,
                        "heatindex_f": 45.5,
                        "dewpoint_c": 5.4,
                        "dewpoint_f": 41.7,
                        "will_it_rain": 0,
                        "chance_of_rain": 0,
                        "will_it_snow": 0,
                        "chance_of_snow": 0,
                        "vis_km": 10,
                        "vis_miles": 6,
                        "gust_mph": 9.4,
                        "gust_kph": 15,
                        "uv": 0.1
                    },
                    {
                        "time_epoch": 1735488000,
                        "time": "2024-12-29 16:00",
                        "temp_c": 6.6,
                        "temp_f": 43.9,
                        "is_day": 0,
                        "condition": {
                            "text": "Clear ",
                            "icon": "//cdn.weatherapi.com/weather/64x64/night/113.png",
                            "code": 1000
                        },
                        "wind_mph": 5.4,
                        "wind_kph": 8.6,
                        "wind_degree": 227,
                        "wind_dir": "SW",
                        "pressure_mb": 1029,
                        "pressure_in": 30.38,
                        "precip_mm": 0,
                        "precip_in": 0,
                        "snow_cm": 0,
                        "humidity": 93,
                        "cloud": 18,
                        "feelslike_c": 4.9,
                        "feelslike_f": 40.8,
                        "windchill_c": 4.9,
                        "windchill_f": 40.8,
                        "heatindex_c": 6.6,
                        "heatindex_f": 43.9,
                        "dewpoint_c": 5.6,
                        "dewpoint_f": 42,
                        "will_it_rain": 0,
                        "chance_of_rain": 0,
                        "will_it_snow": 0,
                        "chance_of_snow": 0,
                        "vis_km": 10,
                        "vis_miles": 6,
                        "gust_mph": 10.2,
                        "gust_kph": 16.5,
                        "uv": 0
                    },
                    {
                        "time_epoch": 1735491600,
                        "time": "2024-12-29 17:00",
                        "temp_c": 6.3,
                        "temp_f": 43.4,
                        "is_day": 0,
                        "condition": {
                            "text": "Mist",
                            "icon": "//cdn.weatherapi.com/weather/64x64/night/143.png",
                            "code": 1030
                        },
                        "wind_mph": 5.6,
                        "wind_kph": 9,
                        "wind_degree": 229,
                        "wind_dir": "SW",
                        "pressure_mb": 1029,
                        "pressure_in": 30.38,
                        "precip_mm": 0,
                        "precip_in": 0,
                        "snow_cm": 0,
                        "humidity": 96,
                        "cloud": 34,
                        "feelslike_c": 4.5,
                        "feelslike_f": 40.1,
                        "windchill_c": 4.5,
                        "windchill_f": 40.1,
                        "heatindex_c": 6.3,
                        "heatindex_f": 43.4,
                        "dewpoint_c": 5.7,
                        "dewpoint_f": 42.2,
                        "will_it_rain": 0,
                        "chance_of_rain": 0,
                        "will_it_snow": 0,
                        "chance_of_snow": 0,
                        "vis_km": 2,
                        "vis_miles": 1,
                        "gust_mph": 10.8,
                        "gust_kph": 17.3,
                        "uv": 0
                    },
                    {
                        "time_epoch": 1735495200,
                        "time": "2024-12-29 18:00",
                        "temp_c": 6.1,
                        "temp_f": 43,
                        "is_day": 0,
                        "condition": {
                            "text": "Mist",
                            "icon": "//cdn.weatherapi.com/weather/64x64/night/143.png",
                            "code": 1030
                        },
                        "wind_mph": 5.6,
                        "wind_kph": 9,
                        "wind_degree": 230,
                        "wind_dir": "SW",
                        "pressure_mb": 1029,
                        "pressure_in": 30.38,
                        "precip_mm": 0,
                        "precip_in": 0,
                        "snow_cm": 0,
                        "humidity": 97,
                        "cloud": 43,
                        "feelslike_c": 4.2,
                        "feelslike_f": 39.6,
                        "windchill_c": 4.2,
                        "windchill_f": 39.6,
                        "heatindex_c": 6.1,
                        "heatindex_f": 43,
                        "dewpoint_c": 5.6,
                        "dewpoint_f": 42.1,
                        "will_it_rain": 0,
                        "chance_of_rain": 0,
                        "will_it_snow": 0,
                        "chance_of_snow": 0,
                        "vis_km": 2,
                        "vis_miles": 1,
                        "gust_mph": 10.8,
                        "gust_kph": 17.4,
                        "uv": 0
                    },
                    {
                        "time_epoch": 1735498800,
                        "time": "2024-12-29 19:00",
                        "temp_c": 5.9,
                        "temp_f": 42.7,
                        "is_day": 0,
                        "condition": {
                            "text": "Mist",
                            "icon": "//cdn.weatherapi.com/weather/64x64/night/143.png",
                            "code": 1030
                        },
                        "wind_mph": 5.6,
                        "wind_kph": 9,
                        "wind_degree": 230,
                        "wind_dir": "SW",
                        "pressure_mb": 1029,
                        "pressure_in": 30.38,
                        "precip_mm": 0,
                        "precip_in": 0,
                        "snow_cm": 0,
                        "humidity": 97,
                        "cloud": 39,
                        "feelslike_c": 4,
                        "feelslike_f": 39.2,
                        "windchill_c": 4,
                        "windchill_f": 39.2,
                        "heatindex_c": 5.9,
                        "heatindex_f": 42.7,
                        "dewpoint_c": 5.5,
                        "dewpoint_f": 41.8,
                        "will_it_rain": 0,
                        "chance_of_rain": 0,
                        "will_it_snow": 0,
                        "chance_of_snow": 0,
                        "vis_km": 2,
                        "vis_miles": 1,
                        "gust_mph": 10.8,
                        "gust_kph": 17.5,
                        "uv": 0
                    },
                    {
                        "time_epoch": 1735502400,
                        "time": "2024-12-29 20:00",
                        "temp_c": 5.8,
                        "temp_f": 42.4,
                        "is_day": 0,
                        "condition": {
                            "text": "Mist",
                            "icon": "//cdn.weatherapi.com/weather/64x64/night/143.png",
                            "code": 1030
                        },
                        "wind_mph": 5.8,
                        "wind_kph": 9.4,
                        "wind_degree": 230,
                        "wind_dir": "SW",
                        "pressure_mb": 1029,
                        "pressure_in": 30.39,
                        "precip_mm": 0,
                        "precip_in": 0,
                        "snow_cm": 0,
                        "humidity": 96,
                        "cloud": 27,
                        "feelslike_c": 3.7,
                        "feelslike_f": 38.6,
                        "windchill_c": 3.7,
                        "windchill_f": 38.6,
                        "heatindex_c": 5.8,
                        "heatindex_f": 42.4,
                        "dewpoint_c": 5.2,
                        "dewpoint_f": 41.4,
                        "will_it_rain": 0,
                        "chance_of_rain": 0,
                        "will_it_snow": 0,
                        "chance_of_snow": 0,
                        "vis_km": 2,
                        "vis_miles": 1,
                        "gust_mph": 11.3,
                        "gust_kph": 18.3,
                        "uv": 0
                    },
                    {
                        "time_epoch": 1735506000,
                        "time": "2024-12-29 21:00",
                        "temp_c": 5.6,
                        "temp_f": 42,
                        "is_day": 0,
                        "condition": {
                            "text": "Mist",
                            "icon": "//cdn.weatherapi.com/weather/64x64/night/143.png",
                            "code": 1030
                        },
                        "wind_mph": 5.8,
                        "wind_kph": 9.4,
                        "wind_degree": 238,
                        "wind_dir": "WSW",
                        "pressure_mb": 1029,
                        "pressure_in": 30.4,
                        "precip_mm": 0,
                        "precip_in": 0,
                        "snow_cm": 0,
                        "humidity": 96,
                        "cloud": 25,
                        "feelslike_c": 3.5,
                        "feelslike_f": 38.2,
                        "windchill_c": 3.5,
                        "windchill_f": 38.2,
                        "heatindex_c": 5.6,
                        "heatindex_f": 42,
                        "dewpoint_c": 5,
                        "dewpoint_f": 40.9,
                        "will_it_rain": 0,
                        "chance_of_rain": 0,
                        "will_it_snow": 0,
                        "chance_of_snow": 0,
                        "vis_km": 2,
                        "vis_miles": 1,
                        "gust_mph": 11.3,
                        "gust_kph": 18.2,
                        "uv": 0
                    },
                    {
                        "time_epoch": 1735509600,
                        "time": "2024-12-29 22:00",
                        "temp_c": 5.4,
                        "temp_f": 41.7,
                        "is_day": 0,
                        "condition": {
                            "text": "Mist",
                            "icon": "//cdn.weatherapi.com/weather/64x64/night/143.png",
                            "code": 1030
                        },
                        "wind_mph": 6,
                        "wind_kph": 9.7,
                        "wind_degree": 234,
                        "wind_dir": "SW",
                        "pressure_mb": 1029,
                        "pressure_in": 30.4,
                        "precip_mm": 0,
                        "precip_in": 0,
                        "snow_cm": 0,
                        "humidity": 96,
                        "cloud": 30,
                        "feelslike_c": 3.2,
                        "feelslike_f": 37.7,
                        "windchill_c": 3.2,
                        "windchill_f": 37.7,
                        "heatindex_c": 5.4,
                        "heatindex_f": 41.7,
                        "dewpoint_c": 4.8,
                        "dewpoint_f": 40.6,
                        "will_it_rain": 0,
                        "chance_of_rain": 0,
                        "will_it_snow": 0,
                        "chance_of_snow": 0,
                        "vis_km": 2,
                        "vis_miles": 1,
                        "gust_mph": 11.8,
                        "gust_kph": 19,
                        "uv": 0
                    },
                    {
                        "time_epoch": 1735513200,
                        "time": "2024-12-29 23:00",
                        "temp_c": 5.2,
                        "temp_f": 41.4,
                        "is_day": 0,
                        "condition": {
                            "text": "Mist",
                            "icon": "//cdn.weatherapi.com/weather/64x64/night/143.png",
                            "code": 1030
                        },
                        "wind_mph": 5.6,
                        "wind_kph": 9,
                        "wind_degree": 238,
                        "wind_dir": "WSW",
                        "pressure_mb": 1030,
                        "pressure_in": 30.4,
                        "precip_mm": 0,
                        "precip_in": 0,
                        "snow_cm": 0,
                        "humidity": 97,
                        "cloud": 48,
                        "feelslike_c": 3.2,
                        "feelslike_f": 37.7,
                        "windchill_c": 3.2,
                        "windchill_f": 37.7,
                        "heatindex_c": 5.2,
                        "heatindex_f": 41.4,
                        "dewpoint_c": 4.7,
                        "dewpoint_f": 40.5,
                        "will_it_rain": 0,
                        "chance_of_rain": 0,
                        "will_it_snow": 0,
                        "chance_of_snow": 0,
                        "vis_km": 2,
                        "vis_miles": 1,
                        "gust_mph": 10.8,
                        "gust_kph": 17.5,
                        "uv": 0
                    }
                ]
            }
        ]
    }
}